cone/__init__.py
cone/deployer.py
cone/proxyhelper.py
cone/queue.py
cone/datasetspider/__init__.py
cone/datasetspider/items.py
cone/datasetspider/spider.py
cone/patterns/__init__.py
cone/patterns/instance.py
cone/patterns/singleton.py
cone/pyquery_ex/__init__.py
cone/pyquery_ex/cssselectpatch.py
cone/pyquery_ex/openers.py
cone/pyquery_ex/pyquery.py
cone/pyquery_ex/text.py
cone/spider/__init__.py
cone/spider/logger.py
cone/spider/pool.py
cone/spider/priority.py
cone/spider/recorder.py
cone/spider/response.py
cone/spider/spider.py
cone/spider/test.py
cone/spider/thread.py
cone/spider/downloader/__init__.py
cone/spider/downloader/downloader.py
cone/spider/item/__init__.py
cone/spider/item/item.py
cone/spider/item/originitem.py
cone/spider/item/ormitem.py
cone/spider_ex/__init__.py
cone/spider_ex/downloader.py
cone/spider_ex/log.py
cone/spider_ex/parser.py
cone/spider_ex/queue.py
cone/spider_ex/recorder.py
cone/spider_ex/request.py
cone/spider_ex/response.py
cone/spider_ex/rule.py
cone/spider_ex/thread.py
cone/spider_ex/worker.py
cone/spider_ex/monitor/__init__.py
cone/spider_ex/monitor/heartbeat.py
cone/sql/__init__.py
cone/sql/mongodb.py
cone/sql/mysql.py
cone/sql/pool.py
cone/sql/sqliter.py
cone/sql/sqlserver.py
cone/tests/__init__.py
cone/tests/resource.py
cone/tests/test.py
cone/tools/__init__.py
cone/tools/encrypter.py
cone/tools/region.py
cone/tools/timeutil.py
cone/tools/timing.py
cone/work/__init__.py
cone/work/yuwoyg/__init__.py
cone/work/yuwoyg/aliyunlog.py
py_cone-0.0.1.dist-info/LICENSE
py_cone-0.0.1.dist-info/METADATA
py_cone-0.0.1.dist-info/WHEEL
py_cone-0.0.1.dist-info/top_level.txt
py_cone-0.0.1.dist-info/RECORD
