Metadata-Version: 2.1
Name: py-cone
Version: 0.0.1
Summary: a simple spider framework, and some tools for spider
Home-page: https://github.com/cone387/cone
Author: Cone
Author-email: 1183008540@qq.com
License: UNKNOWN
Platform: UNKNOWN
Classifier: Programming Language :: Python :: 3
Classifier: License :: OSI Approved :: MIT License
Classifier: Operating System :: OS Independent
